{
  "parent": "swamplands:swamplands/catalyst",
  "criteria": {
    "enter_swamplands": {
      "conditions": {
        "to": "swamplands:swamplands"
      },
      "trigger": "minecraft:changed_dimension"
    }
  },
  "display": {
    "description": {
      "translate": "advancement.swamplands.enter_swamplands.desc"
    },
    "icon": {
      "count": 1,
      "id": "swamplands:deepturf_block"
    },
    "title": {
      "translate": "advancement.swamplands.enter_swamplands.title"
    }
  },
  "requirements": [
    [
      "enter_swamplands"
    ]
  ],
  "sends_telemetry_event": true
}